wifissid.py
wifissid-1.1.4.dist-info/METADATA
wifissid-1.1.4.dist-info/RECORD
wifissid-1.1.4.dist-info/WHEEL
wifissid-1.1.4.dist-info/top_level.txt
