Metadata-Version: 2.1
Name: wifissid
Version: 1.1.4
Summary: Show your connected WiFi SSID on Windows
Home-page: https://pypi.org/project/wifissid/
Author: luxun
Author-email: author@example.com
License: UNKNOWN
Platform: UNKNOWN
Classifier: Programming Language :: Python :: 3
Classifier: License :: OSI Approved :: MIT License
Classifier: Operating System :: Microsoft :: Windows
